dobishem/__init__.py
dobishem/data.py
dobishem/dates.py
dobishem/nested_messages.py
dobishem/storage.py
dobishem-0.0.37.dist-info/LICENSE
dobishem-0.0.37.dist-info/WHEEL
dobishem-0.0.37.dist-info/METADATA
dobishem-0.0.37.dist-info/RECORD
