Metadata-Version: 2.1
Name: dobishem
Version: 0.0.37
Summary: Python utilities for my other packages
Author-email: "John C. G. Sturdy" <jcg.sturdy@gmail.com>
Classifier: License :: OSI Approved :: GNU General Public License v3 or later (GPLv3+)
Requires-Dist: pyyaml
